pycodon_analyzer/__init__.py
pycodon_analyzer/__main__.py
pycodon_analyzer/analysis.py
pycodon_analyzer/cli.py
pycodon_analyzer/extraction.py
pycodon_analyzer/io.py
pycodon_analyzer/plotting.py
pycodon_analyzer/reporting.py
pycodon_analyzer/utils.py
pycodon_analyzer/data/human_codon_usage.csv
pycodon_analyzer/templates/base_template.html
pycodon_analyzer/templates/combined_ca_page_template.html
pycodon_analyzer/templates/correlation_heatmaps_page_template.html
pycodon_analyzer/templates/gene_aggregates_page_template.html
pycodon_analyzer/templates/index_page_template.html
pycodon_analyzer/templates/metadata_plots_page_template.html
pycodon_analyzer/templates/per_gene_rscu_page_template.html
pycodon_analyzer/templates/sequence_metrics_page_template.html
pycodon_analyzer/templates/statistical_comparisons_page_template.html
pycodon_analyzer-1.0.1.dist-info/licenses/LICENSE.txt
pycodon_analyzer-1.0.1.dist-info/METADATA
pycodon_analyzer-1.0.1.dist-info/WHEEL
pycodon_analyzer-1.0.1.dist-info/entry_points.txt
pycodon_analyzer-1.0.1.dist-info/top_level.txt
pycodon_analyzer-1.0.1.dist-info/RECORD
