Metadata-Version: 2.4
Name: pycodon_analyzer
Version: 1.0.1
Summary: A Python tool for comprehensive codon usage analysis and gene alignment extraction.
Author-email: Gabriel Falque <gabfalque@hotmail.fr>
License-Expression: MIT
Project-URL: Homepage, https://github.com/GabrielFalque/pycodon_analyzer
Project-URL: Repository, https://github.com/GabrielFalque/pycodon_analyzer
Keywords: bioinformatics,codon usage,RSCU,CAI,ENC,RCDI,GC content,GRAVY,aromaticity,genomics,sequence analysis,correspondence analysis,bioinformatics tools
Classifier: Development Status :: 5 - Production/Stable
Classifier: Programming Language :: Python :: 3
Classifier: Programming Language :: Python :: 3.8
Classifier: Programming Language :: Python :: 3.9
Classifier: Programming Language :: Python :: 3.10
Classifier: Programming Language :: Python :: 3.11
Classifier: Programming Language :: Python :: 3.12
Classifier: Operating System :: OS Independent
Classifier: Topic :: Scientific/Engineering :: Bio-Informatics
Classifier: Environment :: Console
Classifier: Intended Audience :: Science/Research
Classifier: Environment :: Console
Classifier: Natural Language :: English
Requires-Python: >=3.8
License-File: LICENSE.txt
Requires-Dist: biopython>=1.79
Requires-Dist: pandas>=1.3.0
Requires-Dist: matplotlib>=3.4.0
Requires-Dist: seaborn>=0.11.0
Requires-Dist: numpy>=1.21.0
Requires-Dist: scipy>=1.6.0
Requires-Dist: prince>=0.12.1
Requires-Dist: scikit-learn>=1.0
Requires-Dist: adjustText>=0.8
Requires-Dist: rich>=10.0
Requires-Dist: importlib-resources>=1.0; python_version < "3.9"
Provides-Extra: dev
Requires-Dist: pytest>=7.0; extra == "dev"
Requires-Dist: build; extra == "dev"
Requires-Dist: twine; extra == "dev"
Requires-Dist: mypy; extra == "dev"
Requires-Dist: ruff; extra == "dev"
Provides-Extra: report
Requires-Dist: jinja2>=3.0; extra == "report"
Dynamic: license-file
